varmeth/__init__.py
varmeth-1.0.1.dist-info/METADATA
varmeth-1.0.1.dist-info/WHEEL
varmeth-1.0.1.dist-info/licenses/LICENSE
varmeth-1.0.1.dist-info/RECORD
